redis_auth_lib/__init__.py
redis_auth_lib/auth_service.py
redis_auth_lib-0.1.5.dist-info/METADATA
redis_auth_lib-0.1.5.dist-info/WHEEL
redis_auth_lib-0.1.5.dist-info/RECORD
