Metadata-Version: 2.3
Name: redis-auth-lib
Version: 0.1.5
Summary: 
Author: Lawrence Naumov
Author-email: prostolawr@gmail.com
Requires-Python: >=3.12,<4.0
Classifier: Programming Language :: Python :: 3
Classifier: Programming Language :: Python :: 3.12
Classifier: Programming Language :: Python :: 3.13
Requires-Dist: bcrypt (==4.0.1)
Requires-Dist: fastapi (>=0.115.6,<0.116.0)
Requires-Dist: loguru (>=0.7.3,<0.8.0)
Requires-Dist: passlib[bcrypt] (>=1.7.4,<2.0.0)
Requires-Dist: pydantic-settings (>=2.7.1,<3.0.0)
Requires-Dist: redis (>=5.2.1,<6.0.0)
